jupyter_jsmol/__init__.py
jupyter_jsmol/_frontend.py
jupyter_jsmol/_version.py
jupyter_jsmol/pymatgen.py
jupyter_jsmol/viewer.py
jupyter_jsmol/nbextension/__init__.py
jupyter_jsmol/nbextension/extension.js
jupyter_jsmol/nbextension/extension.js.map
jupyter_jsmol/nbextension/index.js
jupyter_jsmol/nbextension/index.js.LICENSE.txt
jupyter_jsmol/nbextension/index.js.map
jupyter_jsmol/nbextension/jsmol/JSmol.min.js
jupyter_jsmol/nbextension/jsmol/JSmol.min.nojq.js
jupyter_jsmol/nbextension/jsmol/j2s/Jmol.properties
jupyter_jsmol/nbextension/jsmol/j2s/J/Jmol.properties
jupyter_jsmol/nbextension/jsmol/j2s/J/adapter/readers/cif/Cif2DataParser.js
jupyter_jsmol/nbextension/jsmol/j2s/J/adapter/readers/cif/Cif2Reader.js
jupyter_jsmol/nbextension/jsmol/j2s/J/adapter/readers/cif/CifReader.js
jupyter_jsmol/nbextension/jsmol/j2s/J/adapter/readers/cif/MMCifReader.js
jupyter_jsmol/nbextension/jsmol/j2s/J/adapter/readers/cif/MMCifValidationParser.js
jupyter_jsmol/nbextension/jsmol/j2s/J/adapter/readers/cif/MMTFReader.js
jupyter_jsmol/nbextension/jsmol/j2s/J/adapter/readers/cif/MSCifParser.js
jupyter_jsmol/nbextension/jsmol/j2s/J/adapter/readers/cif/MSRdr.js
jupyter_jsmol/nbextension/jsmol/j2s/J/adapter/readers/cif/Subsystem.js
jupyter_jsmol/nbextension/jsmol/j2s/J/adapter/readers/cif/TopoCifParser.js
jupyter_jsmol/nbextension/jsmol/j2s/J/adapter/readers/molxyz/Mol3DReader.js
jupyter_jsmol/nbextension/jsmol/j2s/J/adapter/readers/molxyz/MolReader.js
jupyter_jsmol/nbextension/jsmol/j2s/J/adapter/readers/molxyz/V3000Rdr.js
jupyter_jsmol/nbextension/jsmol/j2s/J/adapter/readers/molxyz/XyzReader.js
jupyter_jsmol/nbextension/jsmol/j2s/J/adapter/readers/more/AFLOWReader.js
jupyter_jsmol/nbextension/jsmol/j2s/J/adapter/readers/more/BinaryDcdReader.js
jupyter_jsmol/nbextension/jsmol/j2s/J/adapter/readers/more/ForceFieldReader.js
jupyter_jsmol/nbextension/jsmol/j2s/J/adapter/readers/more/GromacsReader.js
jupyter_jsmol/nbextension/jsmol/j2s/J/adapter/readers/more/JcampdxReader.js
jupyter_jsmol-2021.9.0.dist-info/METADATA
jupyter_jsmol-2021.9.0.dist-info/WHEEL
jupyter_jsmol-2021.9.0.dist-info/top_level.txt
jupyter_jsmol-2021.9.0.dist-info/RECORD
