Metadata-Version: 2.1
Name: jupyter-jsmol
Version: 2021.9.0
Summary: JSmol viewer widget for Jupyter
Home-page: https://github.com/fekad/jupyter-jsmol
Author: Adam Fekete
Author-email: adam@fekete.co.uk
License: BSD
Keywords: Jupyter,Widgets,IPython
Platform: Linux
Platform: Mac OS X
Platform: Windows
Classifier: Intended Audience :: Developers
Classifier: Intended Audience :: Science/Research
Classifier: Programming Language :: Python
Classifier: Programming Language :: Python :: 3
Classifier: Framework :: Jupyter
Requires-Python: >=3.6
Requires-Dist: ipywidgets (>=7.0.0)
Provides-Extra: docs
Requires-Dist: mkdocs ; extra == 'docs'
Requires-Dist: mkdocs-material ; extra == 'docs'
Provides-Extra: examples
Requires-Dist: ase ; extra == 'examples'
Requires-Dist: matplotlib ; extra == 'examples'
Requires-Dist: plotly ; extra == 'examples'
Provides-Extra: test
Requires-Dist: pytest (>=4.6) ; extra == 'test'
Requires-Dist: pytest-cov ; extra == 'test'
